README.md
setup.py
ContinentInfo/ContinentInfo.py
ContinentInfo/__init__.py
ContinentInfo.egg-info/PKG-INFO
ContinentInfo.egg-info/SOURCES.txt
ContinentInfo.egg-info/dependency_links.txt
ContinentInfo.egg-info/not-zip-safe
ContinentInfo.egg-info/top_level.txt