Metadata-Version: 2.1
Name: ContinentInfo
Version: 1.2
Summary: Get the name of the continent in which a country is located in.
Home-page: UNKNOWN
Author: Rohit Swami
Author-email: rowhitswami1@gmail.com
License: UNKNOWN
Platform: UNKNOWN
